{
  "$schema": "../gen/schemas/desktop-schema.json",
  "identifier": "default",
  "description": "F.R.I.D.A.Y. default capabilities",
  "windows": [
    "main",
    "stats"
  ],
  "permissions": [
    "core:default",
    "core:window:allow-minimize",
    "core:window:allow-maximize",
    "core:window:allow-unmaximize",
    "core:window:allow-close",
    "core:window:allow-is-maximized",
    "core:window:allow-start-dragging",
    "core:window:allow-set-always-on-top",
    "shell:allow-open",
    "shell:allow-execute",
    "core:webview:allow-create-webview-window",
    "core:window:allow-show",
    "core:window:allow-set-focus"
  ]
}
